hxsoup/__init__.py
hxsoup/api.py
hxsoup/broadcast_list.py
hxsoup/broadcast_list.pyi
hxsoup/client.py
hxsoup/dev.py
hxsoup/dev_api.py
hxsoup/exceptions.py
hxsoup/options.py
hxsoup/souptools.py
hxsoup/utils.py
hxsoup-0.6.0.dist-info/METADATA
hxsoup-0.6.0.dist-info/WHEEL
hxsoup-0.6.0.dist-info/licenses/LICENSE
hxsoup-0.6.0.dist-info/RECORD
