Metadata-Version: 2.3
Name: hxsoup
Version: 0.6.0
Summary: Various convenient features related to httpx and BeautifulSoup.
Author-email: ilotoki0804 <ilotoki0804@gmail.com>
License-Expression: MIT
License-File: LICENSE
Keywords: beautifulsoup,beautifulsoup4,bs4,httpx,request,soup
Classifier: License :: OSI Approved :: MIT License
Classifier: Operating System :: OS Independent
Classifier: Programming Language :: Python :: 3
Classifier: Programming Language :: Python :: 3.8
Classifier: Programming Language :: Python :: 3.9
Classifier: Programming Language :: Python :: 3.10
Classifier: Programming Language :: Python :: 3.11
Classifier: Programming Language :: Python :: 3.12
Requires-Python: >=3.9
Requires-Dist: beautifulsoup4>=4.12.3
Requires-Dist: frozendict>=2.4.4
Requires-Dist: httpx>=0.27.2
